codeplot/__init__.py
codeplot/main.py
codeplot/yutils.py
codeplot-1.3.1.dist-info/METADATA
codeplot-1.3.1.dist-info/WHEEL
codeplot-1.3.1.dist-info/top_level.txt
codeplot-1.3.1.dist-info/RECORD
