Metadata-Version: 2.1
Name: codeplot
Version: 1.3.1
Summary: codeplot is a canvas designed for code-driven data exploration where you can plot graphs, data frames, markdown and much more using plain Python
Home-page: https://github.com/codeplot-co/codeplot
Author: Antonio Moura (@antl3x)
Author-email: antonio@codeplot.co
License: AGPL-3.0-or-later
Classifier: Programming Language :: Python :: 3
Requires-Python: >=3.6
Requires-Dist: watchdog >=3.0.0
Requires-Dist: typeid-python >=0.2.2
Requires-Dist: ypy-websocket >=0.12.4
Requires-Dist: asyncio >=3.4.3
Requires-Dist: websockets >=11.0
Requires-Dist: y-py >=0.6.2
